MANIFEST.in
README.rst
setup.py
rotterdam/__init__.py
rotterdam/arbiter.py
rotterdam/client.py
rotterdam/config.py
rotterdam/connection.py
rotterdam/consumer.py
rotterdam/control.py
rotterdam/decorators.py
rotterdam/exceptions.py
rotterdam/features.py
rotterdam/injector.py
rotterdam/master.py
rotterdam/payload.py
rotterdam/proc.py
rotterdam/redis_extensions.py
rotterdam/serialization.py
rotterdam/worker.py
rotterdam/worker_set.py
rotterdam.egg-info/PKG-INFO
rotterdam.egg-info/SOURCES.txt
rotterdam.egg-info/dependency_links.txt
rotterdam.egg-info/entry_points.txt
rotterdam.egg-info/requires.txt
rotterdam.egg-info/top_level.txt
rotterdam/lua/qadd.lua
rotterdam/lua/qfinish.lua
rotterdam/lua/qpop.lua